LICENSE
MANIFEST.in
README.md
setup.cfg
setup.py
TOPSIS_Riya_102083026.egg-info/PKG-INFO
TOPSIS_Riya_102083026.egg-info/SOURCES.txt
TOPSIS_Riya_102083026.egg-info/dependency_links.txt
TOPSIS_Riya_102083026.egg-info/entry_points.txt
TOPSIS_Riya_102083026.egg-info/requires.txt
TOPSIS_Riya_102083026.egg-info/top_level.txt
Topsis_Ranking/101967003.py
Topsis_Ranking/102083026.py
Topsis_Ranking/topsis.py